[{"username":"test","password":"$2y$10$vDPB3PAF2VDzi2ACxYgmbOxQB.h.2Vg8DlCmcanns\/ikNHp29.93."},{"username":"donnytramptramples","password":"$2y$10$OeD4d\/TdXikfhUuVSVB\/EOEzt7TbagDh1GVfhnp\/NPHFiDoVRBm.m"},{"username":"1","password":"$2y$10$vBCCUTecxc0qUvdC8Z.xNeUR4ZqbLeaFmFpQPkWzbt88GJknE9tmi"},{"username":"S\u00a3BAST!\u00a3N","password":"$2y$10$McA5Yor.d878k6eKYnaQ2.4wQvuiet8A0nhOnaqaANXoTvdLFDP.i"},{"username":"Celestial","password":"$2y$10$E4YKN686YlE5eyzYJmaKcOaAmkUTT2YJX4Cx9b7of1D98ftyZZz8."}]